streampq.py
streampq-0.0.48.dist-info/LICENSE
streampq-0.0.48.dist-info/METADATA
streampq-0.0.48.dist-info/WHEEL
streampq-0.0.48.dist-info/top_level.txt
streampq-0.0.48.dist-info/RECORD
