Metadata-Version: 2.1
Name: streampq
Version: 0.0.48
Summary: PostgreSQL adapter to stream results of multi-statement queries without a server-side cursor
Home-page: https://github.com/uktrade/streampq
Author: Department for International Trade
Author-email: sre@digital.trade.gov.uk
Classifier: Programming Language :: Python :: 3
Classifier: License :: OSI Approved :: MIT License
Classifier: Topic :: Database
Requires-Python: >=3.8.0
License-File: LICENSE
